pyrustify-0.2.1.dist-info/METADATA
pyrustify-0.2.1.dist-info/WHEEL
pyrustify-0.2.1.dist-info/license_files/LICENSE
pyrustify/__init__.py
pyrustify/pyrustify.cpython-39-x86_64-linux-gnu.so
pyrustify-0.2.1.dist-info/RECORD
